printfunctions/__init__.py
printfunctions-0.0.0.0.0.0.0.3.dist-info/METADATA
printfunctions-0.0.0.0.0.0.0.3.dist-info/WHEEL
printfunctions-0.0.0.0.0.0.0.3.dist-info/top_level.txt
printfunctions-0.0.0.0.0.0.0.3.dist-info/RECORD
