Metadata-Version: 2.1
Name: printfunctions
Version: 0.0.0.0.0.0.0.3
Summary: ez text handling
Home-page: UNKNOWN
Author: EnderC00kiez
Author-email: EnderC00kiez@outlook.com
License: The Unlicense
Platform: UNKNOWN
